shares/__init__.py
shares/_clique.py
shares/module.MD
shares/shares.s.HTML
shares/$ company/company.s.HTML
shares/_license/license.s.HTML
shares/_status/status.proc.py
shares/_status/checks/1/status_1.py
shares/_status/checks/1/shares/shares 1.s.HTML
shares/_status/checks/1/shares/shares 2.s.HTML
shares/basin/__init__.py
shares/basin/treasury.py
shares/modules/law_dictionary/__init__.py
shares/modules/law_dictionary/dictionary_laws.s.HTML
shares/modules/law_dictionary/status_1.py
shares/modules/law_dictionary/status_broken_1.py
shares-3.1.9.dist-info/METADATA
shares-3.1.9.dist-info/WHEEL
shares-3.1.9.dist-info/entry_points.txt
shares-3.1.9.dist-info/top_level.txt
shares-3.1.9.dist-info/RECORD
