Metadata-Version: 2.1
Name: shares
Version: 3.1.9
Summary: documentation framework that serves all '.s.HTML' that are found in the cwd.
License: GPL 3.0
Project-URL: GitLab, https://gitlab.com/reptilian_climates/modules_series_2/shares
Requires-Dist: body-scan
Requires-Dist: mako
Requires-Dist: flask
Requires-Dist: jsonschema
Requires-Dist: rich
